LICENSE
MANIFEST.in
setup.py
sortroms/__init__.py
sortroms/__main__.py
sortroms/organizer.py
sortroms/utils.py
sortroms.egg-info/PKG-INFO
sortroms.egg-info/SOURCES.txt
sortroms.egg-info/dependency_links.txt
sortroms.egg-info/entry_points.txt
sortroms.egg-info/not-zip-safe
sortroms.egg-info/top_level.txt
sortroms/data/tags.json