Metadata-Version: 1.0
Name: sortroms
Version: 1.2.1
Summary: Python package for sorting emulator ROM files
Home-page: http://github.com/natemara/sortroms
Author: Nate Mara
Author-email: natemara@gmail.com
License: MIT
Platform: UNKNOWN
